{"custom_id":"post_fe416b29aecda805","title":"S\u1ed1ng sao cho \u0111\u1eb9p","about":"H\u00e3y h\u1ecdc c\u00e1ch ch\u1ea5p nh\u1eadn m\u1ecdi b\u1ea5t h\u1ea1nh trong cu\u1ed9c s\u1ed1ng, tin t\u01b0\u1edfng v\u00e0o b\u1ea3nth\u00e2n, \u0111\u1eebng v\u00ec \u201cc\u01a1m \u0111\u1eddi\u201d kh\u00f3 \u0103n m\u00e0 kh\u00f4ng d\u00e1m n\u1ea5u. B\u1ea1n ph\u1ea3i n\u1ebfm tr\u1ea3i \u0111au kh\u1ed5 m\u1edbi c\u00f3 th\u1ec3 tr\u01b0\u1edfng th\u00e0nh.\r\n\r\nKhi b\u1ea1n tr\u01b0\u1edfng th\u00e0nh, g\u1eb7p qua nhi\u1ec1u ng\u01b0\u1eddi, tr\u1ea3i qua nhi\u1ec1u \u0111i\u1ec1u, b\u1ea1n nh\u1ea5t \u0111\u1ecbnh s\u1ebd hi\u1ec3u ra, th\u1ee9 b\u1ea3n th\u00e2n c\u1ea7n n\u1eafm ch\u1eb7t l\u00e0 g\u00ec, c\u0169ng nh\u01b0 th\u1ee9 b\u1ea3n th\u00e2n c\u1ea7n bu\u00f4ng b\u1ecf l\u00e0 g\u00ec.\r\nTh\u1ebf gi\u1edbi n\u00e0y qu\u00e1 r\u1ed9ng l\u1edbn, cu\u1ed9c \u0111\u1eddi l\u1ea1i ng\u1eafn ng\u1ee7i, n\u1ebfu kh\u00f4ng th\u1ec3 l\u00e0m h\u00e0i l\u00f2ng t\u1ea5t c\u1ea3 m\u1ecdi ng\u01b0\u1eddi, tr\u01b0\u1edbc ti\u00ean h\u00e3y l\u00e0m h\u00e0i l\u00f2ng ch\u00ednh m\u00ecnh.","category":"gia_dinh","author":{"name":"Nguy\u1ec5n Lam","avatar":"avatar_683db9bd58bdf.jpg"},"created_at":"2025-06-02 16:48:29","status":"pending","_id":29}