{"custom_id":"post_2dba9f46ce55e289","title":"Cu\u1ed9c \u0111\u1eddi n\u00e0y ch\u00ednh l\u00e0 do b\u1ea1n l\u1ef1a ch\u1ecdn","about":"Ni\u1ec1m vui tinh th\u1ea7n c\u00f3 v\u00f4 v\u00e0n c\u00e1ch \u0111\u1ec3 vui v\u1ebb, b\u1ea1n b\u00e8 c\u0169ng kh\u00f4ng ph\u1ea3i \u0111\u1ebfn v\u1edbi nhau v\u00ec ti\u1ec1n b\u1ea1c. Ki\u1ebfn th\u1ee9c tr\u00ean \u0111\u1eddi c\u0169ng kh\u00f4ng ph\u1ea3i t\u1ed1n k\u00e9m \u0111\u1ec3 \u0111\u01b0\u1ee3c h\u1ecdc.\u0110\u1ec3 an vui c\u0169ng kh\u00f4ng c\u1ea7n qu\u00e1 nhi\u1ec1u ti\u1ec1n \u0111\u1ec3 c\u00f3 th\u1ec3 h\u1ea1nh ph\u00fac.\r\n\u0110\u1ec3 t\u1ed3n t\u1ea1i, \u0111\u1ec3 m\u1ea1nh kh\u1ecfe v\u00e0 vui v\u1ebb, v\u1ec1 b\u1ea3n ch\u1ea5t kh\u00f4ng c\u1ea7n qu\u00e1 nhi\u1ec1u c\u1ee7a c\u1ea3i. Ng\u01b0\u1ee3c l\u1ea1i, t\u1ea1o ra qu\u00e1 nhi\u1ec1u v\u1eadt ch\u1ea5t s\u1ebd sinh ra lo \u00e2u, b\u1ec7nh t\u1eadt v\u00e0 tai h\u1ecda.\r\n            M\u1ee5c \u0111\u00edch c\u1ee7a cu\u1ed9c s\u1ed1ng n\u00e0y kh\u00f4ng ph\u1ea3i \u0111\u1ebfn \u0111\u00e2y \u0111\u1ec3 ch\u00fang ta h\u01a1n thua v\u1edbi ai, ch\u01b0ng di\u1ec7n cho nh\u1eefng ng\u01b0\u1eddi xa l\u1ea1 ng\u01b0\u1ee1ng m\u1ed9, ch\u00fang ta \u0111\u1ebfn \u0111\u00e2y \u0111\u1ec3 vui v\u1ebb, \u0111\u1ec3 s\u1ed1ng m\u1ed9t cu\u1ed9c s\u1ed1ng c\u00f3 \u00edch v\u00e0 gi\u00e1c ng\u1ed9.","category":"truyen_cam_hung","author":{"name":"Xu\u00e2n Lam","avatar":"avatar_683db98f362e1.jpeg"},"created_at":"2025-06-02 16:47:43","status":"approved","_id":28}